swarmauri_parser_beautifulsoupelement/BeautifulSoupElementParser.py
swarmauri_parser_beautifulsoupelement/__init__.py
swarmauri_parser_beautifulsoupelement-0.7.5.dist-info/LICENSE
swarmauri_parser_beautifulsoupelement-0.7.5.dist-info/METADATA
swarmauri_parser_beautifulsoupelement-0.7.5.dist-info/WHEEL
swarmauri_parser_beautifulsoupelement-0.7.5.dist-info/entry_points.txt
swarmauri_parser_beautifulsoupelement-0.7.5.dist-info/RECORD
